{
  "lexicon": 1,
  "id": "com.atproto.admin.getModerationStatuses",
  "defs": {
    "main": {
      "type": "query",
      "description": "View moderation statuses of subjects (record or repo).",
      "parameters": {
        "type": "params",
        "properties": {
          "subject": { "type": "string" },
          "status": {
            "type": "string",
            "knownValues": [
              "com.atproto.admin.defs#acknowledged",
              "com.atproto.admin.defs#muted",
              "com.atproto.admin.defs#escalated",
              "com.atproto.admin.defs#reported",
              "com.atproto.admin.defs#takendown"
            ]
          },
          "limit": {
            "type": "integer",
            "minimum": 1,
            "maximum": 100,
            "default": 50
          },
          "cursor": { "type": "string" }
        }
      },
      "output": {
        "encoding": "application/json",
        "schema": {
          "type": "object",
          "required": ["subjectStatuses"],
          "properties": {
            "cursor": { "type": "string" },
            "subjectStatuses": {
              "type": "array",
              "items": {
                "type": "ref",
                "ref": "com.atproto.admin.defs#subjectStatusView"
              }
            }
          }
        }
      }
    }
  }
}
