{
  "lexicon": 1,
  "id": "com.atproto.simplespace.listMembers",
  "defs": {
    "main": {
      "type": "query",
      "description": "List the members in a space's host-internal member list. Must be called on the space owner's PDS, by the space owner. This reflects the simplespace member list, not a protocol-level reader set.",
      "parameters": {
        "type": "params",
        "required": ["space"],
        "properties": {
          "space": {
            "type": "string",
            "format": "space-uri",
            "description": "Reference to the space."
          },
          "limit": {
            "type": "integer",
            "minimum": 1,
            "maximum": 1000,
            "default": 100,
            "description": "Maximum number of members to return."
          },
          "cursor": {
            "type": "string"
          }
        }
      },
      "output": {
        "encoding": "application/json",
        "schema": {
          "type": "object",
          "required": ["members"],
          "properties": {
            "cursor": {
              "type": "string"
            },
            "members": {
              "type": "array",
              "items": {
                "type": "ref",
                "ref": "#member"
              }
            }
          }
        }
      },
      "errors": [{ "name": "SpaceNotFound" }, { "name": "NotSpaceOwner" }]
    },
    "member": {
      "type": "object",
      "required": ["did"],
      "properties": {
        "did": {
          "type": "string",
          "format": "did"
        }
      }
    }
  }
}
