{
  "lexicon": 1,
  "id": "com.atproto.sync.getRepo",
  "defs": {
    "main": {
      "type": "query",
      "description": "Download a repository export as CAR file. Optionally only a 'diff' since a previous revision. Does not require auth; implemented by PDS.",
      "parameters": {
        "type": "params",
        "required": ["did"],
        "properties": {
          "did": {
            "type": "string",
            "format": "did",
            "description": "The DID of the repo."
          },
          "since": {
            "type": "string",
            "format": "tid",
            "description": "The revision ('rev') of the repo to create a diff from."
          },
          "prefix": {
            "type": "string",
            "description": "For downloading a partial 'slice' of a repository. The prefix of the data key (collection + rkey) to be included in the slice. Currently cannot be used in conjunction with 'since' and if passed together then 'since' will be ignored."
          }
        }
      },
      "output": {
        "encoding": "application/vnd.ipld.car"
      },
      "errors": [
        { "name": "RepoNotFound" },
        { "name": "RepoTakendown" },
        { "name": "RepoSuspended" },
        { "name": "RepoDeactivated" }
      ]
    }
  }
}
