{
  "lexicon": 1,
  "id": "app.bsky.feed.getVotes",
  "type": "query",
  "parameters": {
    "type": "object",
    "required": ["uri"],
    "properties": {
      "uri": {"type": "string"},
      "cid": {"type": "string"},
      "direction": {"type": "string", "enum": ["up", "down"]},
      "limit": {"type": "integer", "maximum": 100},
      "before": {"type": "string"}
    }
  },
  "output": {
    "encoding": "application/json",
    "schema": {
      "type": "object",
      "required": ["uri", "votes"],
      "properties": {
        "uri": {"type": "string"},
        "cid": {"type": "string"},
        "cursor": {"type": "string"},
        "votes": {
          "type": "array",
          "items": {
            "type": "object",
            "required": ["direction", "indexedAt", "createdAt", "actor"],
            "properties": {
              "direction": {"type": "string", "enum": ["up", "down"]},
              "indexedAt": {"type": "string", "format": "date-time"},
              "createdAt": {"type": "string", "format": "date-time"},
              "actor": {"$ref": "#/defs/actor"}
            }
          }
        }
      }
    }
  },
  "defs": {
    "actor": {
      "type": "object",
      "required": ["did", "declaration", "handle"],
      "properties": {
        "did": {"type": "string"},
        "declaration": {"$ref": "#/defs/declaration"},
        "handle": {"type": "string"},
        "displayName": {
          "type": "string",
          "maxLength": 64
        }
      }
    },
    "declaration": {
      "type": "object",
      "required": ["cid", "actorType"],
      "properties": {
        "cid": {"type": "string"},
        "actorType": {
          "oneOf": [
            {"$ref": "#/defs/actorKnown"},
            {"$ref": "#/defs/actorUnknown"}
          ]
        }
      }
    },
    "actorKnown": {
      "type": "string",
      "enum": ["app.bsky.system.actorUser", "app.bsky.system.actorScene"]
    },
    "actorUnknown": {
      "type": "string",
      "not": {"enum": ["app.bsky.system.actorUser", "app.bsky.system.actorScene"]}
    }
  }
}
